streamunolib/__init__.py
streamunolib/decorators.py
streamunolib/media_types.py
streamunolib/py.typed
streamunolib/types.py
streamunolib-0.4.3.dist-info/WHEEL
streamunolib-0.4.3.dist-info/METADATA
streamunolib-0.4.3.dist-info/RECORD
