Metadata-Version: 2.1
Name: streamunolib
Version: 0.4.3
Summary: Library of generic transform components.
Author: Pierre Chanial
Author-email: pierre.chanial@apc.in2p3.fr
Requires-Python: >=3.8,<4.0
Classifier: Programming Language :: Python :: 3
Classifier: Programming Language :: Python :: 3.10
Classifier: Programming Language :: Python :: 3.8
Classifier: Programming Language :: Python :: 3.9
Requires-Dist: typing-extensions (>=4.2.0,<5.0.0)
